usethis/.gitignore
usethis/__init__.py
usethis/__main__.py
usethis/_config.py
usethis/_config_file.py
usethis/_console.py
usethis/_deps.py
usethis/_init.py
usethis/_io.py
usethis/_subprocess.py
usethis/_test.py
usethis/_version.py
usethis/errors.py
usethis/py.typed
usethis/_core/__init__.py
usethis/_core/author.py
usethis/_core/badge.py
usethis/_core/browse.py
usethis/_core/ci.py
usethis/_core/docstyle.py
usethis/_core/list.py
usethis/_core/readme.py
usethis/_core/rule.py
usethis/_core/show.py
usethis/_core/status.py
usethis/_core/tool.py
usethis/_integrations/__init__.py
usethis/_integrations/backend/__init__.py
usethis/_integrations/backend/dispatch.py
usethis/_integrations/backend/poetry/__init__.py
usethis/_integrations/backend/poetry/used.py
usethis/_integrations/backend/uv/__init__.py
usethis/_integrations/backend/uv/available.py
usethis/_integrations/backend/uv/call.py
usethis/_integrations/backend/uv/deps.py
usethis/_integrations/backend/uv/errors.py
usethis/_integrations/backend/uv/init.py
usethis/_integrations/backend/uv/link_mode.py
usethis/_integrations/backend/uv/lockfile.py
usethis/_integrations/backend/uv/python.py
usethis/_integrations/backend/uv/toml.py
usethis/_integrations/backend/uv/used.py
usethis/_integrations/backend/uv/version.py
usethis/_integrations/ci/__init__.py
usethis/_integrations/ci/bitbucket/__init__.py
usethis/_integrations/ci/bitbucket/anchor.py
usethis/_integrations/ci/bitbucket/cache.py
usethis/_integrations/ci/bitbucket/config.py
usethis/_integrations/ci/bitbucket/errors.py
usethis/_integrations/ci/bitbucket/init.py
usethis/_integrations/ci/bitbucket/pipeweld.py
usethis/_integrations/ci/bitbucket/schema.py
usethis/_integrations/ci/bitbucket/schema_utils.py
usethis/_integrations/ci/bitbucket/steps.py
usethis/_integrations/ci/bitbucket/used.py
usethis/_integrations/ci/bitbucket/yaml.py
usethis/_integrations/ci/github/__init__.py
usethis/_integrations/ci/github/errors.py
usethis/_integrations/ci/github/tags.py
usethis-0.18.0.dist-info/METADATA
usethis-0.18.0.dist-info/WHEEL
usethis-0.18.0.dist-info/entry_points.txt
usethis-0.18.0.dist-info/licenses/LICENSE
usethis-0.18.0.dist-info/RECORD
