Metadata-Version: 2.4
Name: usethis
Version: 0.18.0
Summary: Automate Python project setup and development tasks that are otherwise performed manually.
Project-URL: Source Code, https://github.com/usethis-python/usethis-python
Project-URL: Documentation, https://usethis.readthedocs.io/en/stable/
Project-URL: Bug Tracker, https://github.com/usethis-python/usethis-python/issues
Project-URL: Releases, https://github.com/usethis-python/usethis-python/releases
Project-URL: Source Archive, https://github.com/usethis-python/usethis-python/archive/75e61d4d3653b4bdc6b478fb0b25519d9d68c0fb.zip
Author-email: Nathan McDougall <nathan.j.mcdougall@gmail.com>
License: MIT License
License-File: LICENSE
Keywords: init,project,setup,start,usethis
Classifier: Development Status :: 3 - Alpha
Classifier: Environment :: Console
Classifier: Intended Audience :: Developers
Classifier: License :: OSI Approved :: MIT License
Classifier: Operating System :: OS Independent
Classifier: Programming Language :: Python :: 3 :: Only
Classifier: Programming Language :: Python :: 3.10
Classifier: Programming Language :: Python :: 3.11
Classifier: Programming Language :: Python :: 3.12
Classifier: Programming Language :: Python :: 3.13
Classifier: Programming Language :: Python :: 3.14
Classifier: Topic :: Software Development
Classifier: Topic :: Software Development :: Quality Assurance
Classifier: Topic :: Software Development :: Testing
Classifier: Typing :: Typed
Requires-Python: >=3.10
Requires-Dist: configupdater>=3.2
Requires-Dist: grimp>=3.14
Requires-Dist: mergedeep>=1.3.4
Requires-Dist: packaging>=20.9
Requires-Dist: pydantic>=2.5.0
Requires-Dist: requests>=2.26.0
Requires-Dist: rich>=9.6.1
Requires-Dist: ruamel-yaml!=0.18.13,!=0.18.14,!=0.18.15,!=0.18.16,!=0.18.17,>=0.16.13
Requires-Dist: tomlkit>=0.13.3
Requires-Dist: typer>=0.12.4
Requires-Dist: typing-extensions>=3.10.0.0
